tinypackage/__init__.py
tinypackage-1.0.dist-info/DESCRIPTION.rst
tinypackage-1.0.dist-info/METADATA
tinypackage-1.0.dist-info/RECORD
tinypackage-1.0.dist-info/WHEEL
tinypackage-1.0.dist-info/metadata.json
tinypackage-1.0.dist-info/top_level.txt
