Metadata-Version: 1.0
Name: tinypackage
Version: 1.0
Summary: say hello!
Home-page: http://github.com/haiwangyang/tinypackage
Author: Haiwang Yang
Author-email: haiwangyang@gmail.com
License: MIT
Platform: UNKNOWN
